{
  "image_width": 1280,
  "image_height": 1024,
  "created": "2026-07-19T16:17:22",
  "notes": "16 vial(s) drawn by hand on the live feed; face(s) A, B share identical coordinates",
  "faces": {
    "A": {
      "name": "A",
      "vials": [
        {
          "id": 1,
          "row": 0,
          "col": 0,
          "x": 95,
          "y": 49,
          "w": 123,
          "h": 286,
          "present": true,
          "quad": null,
          "polygon": [
            [
              115,
              57
            ],
            [
              218,
              49
            ],
            [
              195,
              335
            ],
            [
              95,
              327
            ]
          ]
        },
        {
          "id": 2,
          "row": 0,
          "col": 1,
          "x": 235,
          "y": 55,
          "w": 123,
          "h": 283,
          "present": true,
          "quad": null,
          "polygon": [
            [
              254,
              58
            ],
            [
              358,
              55
            ],
            [
              350,
              338
            ],
            [
              235,
              338
            ]
          ]
        },
        {
          "id": 3,
          "row": 0,
          "col": 2,
          "x": 396,
          "y": 60,
          "w": 111,
          "h": 281,
          "present": true,
          "quad": null,
          "polygon": [
            [
              402,
              60
            ],
            [
              507,
              65
            ],
            [
              503,
              338
            ],
            [
              396,
              341
            ]
          ]
        },
        {
          "id": 4,
          "row": 0,
          "col": 3,
          "x": 545,
          "y": 66,
          "w": 107,
          "h": 272,
          "present": true,
          "quad": null,
          "polygon": [
            [
              555,
              66
            ],
            [
              648,
              69
            ],
            [
              652,
              329
            ],
            [
              545,
              338
            ]
          ]
        },
        {
          "id": 5,
          "row": 0,
          "col": 4,
          "x": 698,
          "y": 76,
          "w": 111,
          "h": 269,
          "present": true,
          "quad": null,
          "polygon": [
            [
              698,
              76
            ],
            [
              809,
              83
            ],
            [
              808,
              338
            ],
            [
              709,
              345
            ]
          ]
        },
        {
          "id": 6,
          "row": 0,
          "col": 5,
          "x": 840,
          "y": 78,
          "w": 114,
          "h": 278,
          "present": true,
          "quad": null,
          "polygon": [
            [
              848,
              78
            ],
            [
              954,
              93
            ],
            [
              950,
              356
            ],
            [
              840,
              353
            ]
          ]
        },
        {
          "id": 7,
          "row": 0,
          "col": 6,
          "x": 981,
          "y": 97,
          "w": 88,
          "h": 255,
          "present": true,
          "quad": null,
          "polygon": [
            [
              985,
              97
            ],
            [
              1067,
              108
            ],
            [
              1069,
              345
            ],
            [
              981,
              352
            ]
          ]
        },
        {
          "id": 8,
          "row": 0,
          "col": 7,
          "x": 1105,
          "y": 108,
          "w": 80,
          "h": 257,
          "present": true,
          "quad": null,
          "polygon": [
            [
              1115,
              108
            ],
            [
              1181,
              119
            ],
            [
              1185,
              365
            ],
            [
              1105,
              352
            ]
          ]
        },
        {
          "id": 9,
          "row": 1,
          "col": 0,
          "x": 99,
          "y": 571,
          "w": 105,
          "h": 279,
          "present": true,
          "quad": null,
          "polygon": [
            [
              99,
              574
            ],
            [
              199,
              571
            ],
            [
              204,
              844
            ],
            [
              116,
              850
            ]
          ]
        },
        {
          "id": 10,
          "row": 1,
          "col": 1,
          "x": 248,
          "y": 569,
          "w": 102,
          "h": 279,
          "present": true,
          "quad": null,
          "polygon": [
            [
              248,
              569
            ],
            [
              350,
              575
            ],
            [
              350,
              844
            ],
            [
              258,
              848
            ]
          ]
        },
        {
          "id": 11,
          "row": 1,
          "col": 2,
          "x": 407,
          "y": 575,
          "w": 91,
          "h": 272,
          "present": true,
          "quad": null,
          "polygon": [
            [
              407,
              575
            ],
            [
              498,
              578
            ],
            [
              488,
              847
            ],
            [
              409,
              847
            ]
          ]
        },
        {
          "id": 12,
          "row": 1,
          "col": 3,
          "x": 548,
          "y": 576,
          "w": 93,
          "h": 269,
          "present": true,
          "quad": null,
          "polygon": [
            [
              553,
              576
            ],
            [
              641,
              579
            ],
            [
              634,
              845
            ],
            [
              548,
              843
            ]
          ]
        },
        {
          "id": 13,
          "row": 1,
          "col": 4,
          "x": 691,
          "y": 578,
          "w": 94,
          "h": 272,
          "present": true,
          "quad": null,
          "polygon": [
            [
              691,
              578
            ],
            [
              782,
              579
            ],
            [
              785,
              848
            ],
            [
              695,
              850
            ]
          ]
        },
        {
          "id": 14,
          "row": 1,
          "col": 5,
          "x": 833,
          "y": 579,
          "w": 94,
          "h": 266,
          "present": true,
          "quad": null,
          "polygon": [
            [
              841,
              579
            ],
            [
              927,
              580
            ],
            [
              927,
              833
            ],
            [
              833,
              845
            ]
          ]
        },
        {
          "id": 15,
          "row": 1,
          "col": 6,
          "x": 970,
          "y": 586,
          "w": 107,
          "h": 264,
          "present": true,
          "quad": null,
          "polygon": [
            [
              974,
              588
            ],
            [
              1077,
              586
            ],
            [
              1063,
              832
            ],
            [
              970,
              850
            ]
          ]
        },
        {
          "id": 16,
          "row": 1,
          "col": 7,
          "x": 1094,
          "y": 591,
          "w": 90,
          "h": 244,
          "present": true,
          "quad": null,
          "polygon": [
            [
              1096,
              592
            ],
            [
              1184,
              591
            ],
            [
              1166,
              835
            ],
            [
              1094,
              835
            ]
          ]
        }
      ],
      "illum_mask_path": "illum_mask_A.png",
      "marker": {
        "source": "live_vial_selector",
        "n_vials": 16,
        "image_size": [
          1280,
          1024
        ],
        "band_templates": [
          [
            0.043859649122807015,
            0.046663226694186447,
            0.05701754385964912,
            0.06140350877192982,
            0.06140350877192982,
            0.07017543859649122,
            0.0738390092879257,
            0.07456140350877193,
            0.06578947368421052,
            0.06578947368421052,
            0.08333333333333333,
            0.07469900240798073,
            0.0804437564499484,
            0.07894736842105263,
            0.1006535947712418,
            0.1839525283797729,
            0.18859649122807018,
            0.2301169590643275,
            0.2894736842105263,
            1.0,
            1.0,
            1.0,
            1.0,
            1.0,
            1.0,
            1.0,
            1.0,
            1.0,
            1.0,
            1.0,
            1.0,
            1.0,
            1.0,
            1.0,
            1.0,
            1.0,
            1.0,
            1.0,
            1.0,
            1.0,
            1.0,
            1.0,
            1.0,
            1.0,
            1.0,
            1.0,
            1.0,
            1.0,
            1.0,
            1.0,
            1.0,
            1.0,
            1.0,
            1.0,
            1.0,
            1.0,
            1.0,
            1.0,
            1.0,
            1.0,
            1.0,
            1.0,
            1.0,
            1.0,
            1.0,
            1.0,
            1.0,
            0.513347093223258,
            0.21345029239766078,
            0.15789473684210525,
            0.1250429996560027,
            0.11403508771929824,
            0.10954592363261102,
            0.10087719298245613,
            0.09078087375300993,
            0.08333333333333333,
            0.07201582387340907,
            0.06140350877192982,
            0.06140350877192982,
            0.06578947368421052,
            0.06578947368421052,
            0.06578947368421052,
            0.07017543859649122,
            0.07456140350877193,
            0.07760577915376674,
            0.08771929824561403,
            0.09210526315789473,
            0.09649122807017543,
            0.10197798417612658,
            0.10964912280701754,
            0.12074303405572744,
            0.13231854145166846,
            0.1562091503267974,
            0.18962848297213603,
            0.36828345373236576,
            1.0,
            1.0,
            1.0,
            1.0,
            1.0,
            1.0,
            1.0,
            1.0,
            1.0,
            1.0,
            1.0,
            1.0,
            1.0,
            1.0,
            1.0,
            1.0,
            1.0,
            1.0,
            1.0,
            1.0,
            1.0,
            1.0,
            1.0,
            1.0,
            1.0,
            1.0,
            1.0,
            1.0,
            1.0,
            1.0,
            1.0,
            1.0,
            1.0,
            1.0,
            1.0,
            1.0,
            1.0,
            1.0,
            0.9991056071551436,
            0.4900584795321678,
            0.1865325077399377,
            0.16228070175438597,
            0.13907808737530114,
            0.08586171310629534,
            0.0620571035431718,
            0.05263157894736842,
            0.04824561403508772,
            0.04824561403508772,
            0.045648434812521364,
            0.04803921568627469,
            0.04686962504299941,
            0.04824561403508772,
            0.03962848297213608,
            0.039473684210526314,
            0.0624699002407981,
            0.07017543859649122,
            0.07017543859649122,
            0.08333333333333333,
            0.07456140350877193,
            0.08525971792225637,
            0.09210526315789473,
            0.08895768833849316,
            0.09805641554867568,
            0.10526315789473684,
            0.09649122807017543,
            0.1020811833505331,
            0.10964912280701754,
            0.10572755417956614,
            0.1123495012039909,
            0.11984864121087101,
            0.12280701754385964,
            0.1237702098383214,
            0.13814929480564156,
            0.14473684210526316,
            0.14473684210526316,
            0.16228070175438597,
            0.23978328173374347,
            0.8705538355692976,
            1.0,
            1.0,
            1.0,
            1.0,
            1.0,
            1.0,
            1.0,
            1.0,
            1.0,
            1.0,
            1.0,
            1.0,
            1.0,
            1.0,
            1.0,
            1.0,
            1.0,
            1.0,
            1.0,
            1.0,
            1.0,
            1.0,
            1.0,
            1.0,
            1.0,
            1.0,
            1.0,
            1.0,
            1.0,
            1.0,
            1.0,
            1.0,
            1.0,
            1.0,
            1.0,
            1.0,
            1.0,
            1.0,
            1.0,
            1.0,
            1.0,
            1.0,
            1.0,
            1.0,
            1.0,
            1.0,
            0.6597007223942193,
            0.2624699002407982,
            0.1807017543859651,
            0.21243550051599513,
            0.2085483316133489,
            0.11957344341245364,
            0.08849329205366385,
            0.07017543859649122,
            0.06623667010663924,
            0.06578947368421052,
            0.06140350877192982,
            0.06140350877192982,
            0.06140350877192982,
            0.06140350877192982,
            0.07401100791193621,
            0.07270381836945324,
            0.07206742346061258,
            0.08269693842449267,
            0.09649122807017543,
            0.10643274853801163,
            0.12519779841761247,
            0.17389060887512842,
            0.29305125558995204,
            0.9374957000343878,
            1.0,
            1.0,
            1.0,
            1.0,
            1.0,
            1.0,
            1.0,
            1.0,
            1.0,
            1.0,
            1.0,
            1.0,
            1.0
          ],
          [
            1.0,
            1.0,
            1.0,
            1.0,
            1.0,
            1.0,
            1.0,
            1.0,
            1.0,
            1.0,
            1.0,
            1.0,
            1.0,
            1.0,
            1.0,
            1.0,
            1.0,
            1.0,
            1.0,
            1.0,
            1.0,
            1.0,
            1.0,
            1.0,
            1.0,
            1.0,
            1.0,
            1.0,
            1.0,
            0.2551771585827319,
            0.12564499484004132,
            0.08852769177846578,
            0.06379428964568284,
            0.05263157894736842,
            0.053801169590643266,
            0.05263157894736842,
            0.06140350877192982,
            0.06425868593051258,
            0.058290333677330546,
            0.06547987616099074,
            0.07705538355693152,
            0.08680770553835565,
            0.08333333333333333,
            0.08108015135878906,
            0.07949776401788786,
            0.08668730650154792,
            0.08949088407292742,
            0.0922944616443068,
            0.10386996904024769,
            0.12124183006535941,
            0.14017887856897146,
            0.16754385964912277,
            0.18735810113519105,
            0.31389748882008917,
            1.0,
            1.0,
            1.0,
            1.0,
            1.0,
            1.0,
            1.0,
            1.0,
            1.0,
            1.0,
            1.0,
            1.0,
            1.0,
            1.0,
            1.0,
            1.0,
            1.0,
            1.0,
            1.0,
            1.0,
            1.0,
            1.0,
            1.0,
            1.0,
            1.0,
            1.0,
            1.0,
            1.0,
            1.0,
            1.0,
            1.0,
            1.0,
            1.0,
            1.0,
            1.0,
            1.0,
            1.0,
            1.0,
            1.0,
            1.0,
            1.0,
            1.0,
            1.0,
            1.0,
            1.0,
            1.0,
            1.0,
            1.0,
            1.0,
            1.0,
            1.0,
            1.0,
            0.8373409012727911,
            0.31861025111799196,
            0.24484004127967046,
            0.1900240798073615,
            0.17707258341933266,
            0.16228070175438597,
            0.15789473684210525,
            0.15789473684210525,
            0.16228070175438597,
            0.16219470244238052,
            0.15789473684210525,
            0.1544375644994839,
            0.14912280701754385,
            0.16228070175438597,
            0.1635706914344686,
            0.15789473684210525,
            0.15782593739250092,
            0.15515995872033023,
            0.15789473684210525,
            0.15746474028207763,
            0.16228070175438597,
            0.14473684210526316,
            0.1323701410388717,
            0.12352941176470622,
            0.114895080839353,
            0.13481252149982806,
            0.12497420020639836,
            0.07894736842105263,
            0.07017543859649122,
            0.06578947368421052,
            0.06988304093567253,
            0.05701754385964912,
            0.043859649122807015,
            0.043859649122807015,
            0.039473684210526314,
            0.04442724458204332,
            0.05263157894736842,
            0.06319229446164418,
            0.09669762641898845,
            0.15402476780185612,
            0.3092535259717962,
            0.9307017543859721,
            1.0,
            1.0,
            1.0,
            1.0,
            1.0,
            1.0,
            1.0,
            1.0,
            1.0,
            1.0,
            1.0,
            1.0,
            1.0,
            1.0,
            1.0,
            1.0,
            1.0,
            1.0,
            1.0,
            1.0,
            1.0,
            1.0,
            1.0,
            1.0,
            1.0,
            1.0,
            1.0,
            1.0,
            1.0,
            1.0,
            1.0,
            1.0,
            1.0,
            1.0,
            1.0,
            0.708771929824555,
            0.26585827313381494,
            0.2992776057791538,
            0.20985552115583136,
            0.15526315789473724,
            0.1308221534227728,
            0.12007223942208511,
            0.11842105263157894,
            0.11482628138974915,
            0.11403508771929824,
            0.11288269693842454,
            0.12719298245614036,
            0.12719298245614036,
            0.12280701754385964,
            0.11842105263157894,
            0.12280701754385964,
            0.11842105263157894,
            0.12211902304781574,
            0.10964912280701754,
            0.1178878568971448,
            0.11403508771929824,
            0.14736842105263118,
            0.18859649122807018,
            0.20049879600963108,
            0.2844685242518036,
            0.6703646370829119,
            1.0,
            1.0,
            1.0,
            1.0,
            1.0,
            1.0,
            1.0,
            1.0,
            1.0,
            1.0,
            1.0,
            1.0,
            1.0,
            1.0,
            1.0,
            1.0,
            1.0,
            1.0,
            1.0,
            1.0,
            1.0,
            1.0,
            1.0,
            1.0,
            1.0,
            1.0,
            1.0,
            1.0,
            1.0,
            1.0,
            1.0,
            1.0,
            1.0,
            1.0,
            1.0,
            1.0,
            1.0,
            1.0,
            1.0,
            1.0,
            1.0,
            1.0,
            1.0,
            0.3995356037151684,
            0.25488476092191215,
            0.2057791537667697,
            0.17543859649122806
          ]
        ],
        "band_detector": {
          "band_rows": null,
          "bright_percentile": 99.5,
          "min_run_px": 25,
          "params": {
            "search_frac": [
              0.2,
              0.8
            ],
            "dark_percentile": 5.0,
            "bright_rel": 0.9,
            "strip_run_frac": 0.25,
            "row_join_gap": 3,
            "min_strip_h": 6,
            "max_strip_h": 110,
            "max_strip_gap": 160,
            "min_peak_frac": 0.02,
            "min_dynamic_range": 20.0,
            "median_blur": 3,
            "profile_length": 256,
            "lit_frac_level": 0.35,
            "max_lag": 8,
            "min_score": 0.45,
            "min_margin": 0.15,
            "use_swap_check": true,
            "block_level": 0.5,
            "close_px": 21,
            "edge_tol_px": 12
          }
        },
        "band_learned": "2026-07-19T16:18:21",
        "band_dwells": 2
      }
    },
    "B": {
      "name": "B",
      "vials": [
        {
          "id": 1,
          "row": 0,
          "col": 0,
          "x": 95,
          "y": 49,
          "w": 123,
          "h": 286,
          "present": true,
          "quad": null,
          "polygon": [
            [
              115,
              57
            ],
            [
              218,
              49
            ],
            [
              195,
              335
            ],
            [
              95,
              327
            ]
          ]
        },
        {
          "id": 2,
          "row": 0,
          "col": 1,
          "x": 235,
          "y": 55,
          "w": 123,
          "h": 283,
          "present": true,
          "quad": null,
          "polygon": [
            [
              254,
              58
            ],
            [
              358,
              55
            ],
            [
              350,
              338
            ],
            [
              235,
              338
            ]
          ]
        },
        {
          "id": 3,
          "row": 0,
          "col": 2,
          "x": 396,
          "y": 60,
          "w": 111,
          "h": 281,
          "present": true,
          "quad": null,
          "polygon": [
            [
              402,
              60
            ],
            [
              507,
              65
            ],
            [
              503,
              338
            ],
            [
              396,
              341
            ]
          ]
        },
        {
          "id": 4,
          "row": 0,
          "col": 3,
          "x": 545,
          "y": 66,
          "w": 107,
          "h": 272,
          "present": true,
          "quad": null,
          "polygon": [
            [
              555,
              66
            ],
            [
              648,
              69
            ],
            [
              652,
              329
            ],
            [
              545,
              338
            ]
          ]
        },
        {
          "id": 5,
          "row": 0,
          "col": 4,
          "x": 698,
          "y": 76,
          "w": 111,
          "h": 269,
          "present": true,
          "quad": null,
          "polygon": [
            [
              698,
              76
            ],
            [
              809,
              83
            ],
            [
              808,
              338
            ],
            [
              709,
              345
            ]
          ]
        },
        {
          "id": 6,
          "row": 0,
          "col": 5,
          "x": 840,
          "y": 78,
          "w": 114,
          "h": 278,
          "present": true,
          "quad": null,
          "polygon": [
            [
              848,
              78
            ],
            [
              954,
              93
            ],
            [
              950,
              356
            ],
            [
              840,
              353
            ]
          ]
        },
        {
          "id": 7,
          "row": 0,
          "col": 6,
          "x": 981,
          "y": 97,
          "w": 88,
          "h": 255,
          "present": true,
          "quad": null,
          "polygon": [
            [
              985,
              97
            ],
            [
              1067,
              108
            ],
            [
              1069,
              345
            ],
            [
              981,
              352
            ]
          ]
        },
        {
          "id": 8,
          "row": 0,
          "col": 7,
          "x": 1105,
          "y": 108,
          "w": 80,
          "h": 257,
          "present": true,
          "quad": null,
          "polygon": [
            [
              1115,
              108
            ],
            [
              1181,
              119
            ],
            [
              1185,
              365
            ],
            [
              1105,
              352
            ]
          ]
        },
        {
          "id": 9,
          "row": 1,
          "col": 0,
          "x": 99,
          "y": 571,
          "w": 105,
          "h": 279,
          "present": true,
          "quad": null,
          "polygon": [
            [
              99,
              574
            ],
            [
              199,
              571
            ],
            [
              204,
              844
            ],
            [
              116,
              850
            ]
          ]
        },
        {
          "id": 10,
          "row": 1,
          "col": 1,
          "x": 248,
          "y": 569,
          "w": 102,
          "h": 279,
          "present": true,
          "quad": null,
          "polygon": [
            [
              248,
              569
            ],
            [
              350,
              575
            ],
            [
              350,
              844
            ],
            [
              258,
              848
            ]
          ]
        },
        {
          "id": 11,
          "row": 1,
          "col": 2,
          "x": 407,
          "y": 575,
          "w": 91,
          "h": 272,
          "present": true,
          "quad": null,
          "polygon": [
            [
              407,
              575
            ],
            [
              498,
              578
            ],
            [
              488,
              847
            ],
            [
              409,
              847
            ]
          ]
        },
        {
          "id": 12,
          "row": 1,
          "col": 3,
          "x": 548,
          "y": 576,
          "w": 93,
          "h": 269,
          "present": true,
          "quad": null,
          "polygon": [
            [
              553,
              576
            ],
            [
              641,
              579
            ],
            [
              634,
              845
            ],
            [
              548,
              843
            ]
          ]
        },
        {
          "id": 13,
          "row": 1,
          "col": 4,
          "x": 691,
          "y": 578,
          "w": 94,
          "h": 272,
          "present": true,
          "quad": null,
          "polygon": [
            [
              691,
              578
            ],
            [
              782,
              579
            ],
            [
              785,
              848
            ],
            [
              695,
              850
            ]
          ]
        },
        {
          "id": 14,
          "row": 1,
          "col": 5,
          "x": 833,
          "y": 579,
          "w": 94,
          "h": 266,
          "present": true,
          "quad": null,
          "polygon": [
            [
              841,
              579
            ],
            [
              927,
              580
            ],
            [
              927,
              833
            ],
            [
              833,
              845
            ]
          ]
        },
        {
          "id": 15,
          "row": 1,
          "col": 6,
          "x": 970,
          "y": 586,
          "w": 107,
          "h": 264,
          "present": true,
          "quad": null,
          "polygon": [
            [
              974,
              588
            ],
            [
              1077,
              586
            ],
            [
              1063,
              832
            ],
            [
              970,
              850
            ]
          ]
        },
        {
          "id": 16,
          "row": 1,
          "col": 7,
          "x": 1094,
          "y": 591,
          "w": 90,
          "h": 244,
          "present": true,
          "quad": null,
          "polygon": [
            [
              1096,
              592
            ],
            [
              1184,
              591
            ],
            [
              1166,
              835
            ],
            [
              1094,
              835
            ]
          ]
        }
      ],
      "illum_mask_path": "illum_mask_B.png",
      "marker": {
        "source": "live_vial_selector",
        "n_vials": 16,
        "image_size": [
          1280,
          1024
        ],
        "band_templates": [
          [
            1.0,
            1.0,
            1.0,
            1.0,
            1.0,
            1.0,
            1.0,
            1.0,
            1.0,
            1.0,
            1.0,
            1.0,
            1.0,
            1.0,
            1.0,
            1.0,
            1.0,
            1.0,
            1.0,
            1.0,
            1.0,
            1.0,
            1.0,
            1.0,
            1.0,
            1.0,
            0.34399456752397817,
            0.0773109243697479,
            0.04607418725065789,
            0.033290892114421516,
            0.026228673287496833,
            0.021016891605126854,
            0.017316017316017316,
            0.017316017316017316,
            0.017316017316017316,
            0.013411425176131043,
            0.017316017316017316,
            0.017316017316017316,
            0.012987012987012988,
            0.01568627450980393,
            0.017316017316017316,
            0.017316017316017316,
            0.017316017316017316,
            0.017316017316017316,
            0.013937696290637465,
            0.017316017316017316,
            0.017316017316017316,
            0.0202359731771497,
            0.021645021645021644,
            0.025974025974025976,
            0.030303030303030304,
            0.11515151515151427,
            0.9489007724301877,
            1.0,
            1.0,
            1.0,
            1.0,
            1.0,
            1.0,
            1.0,
            1.0,
            1.0,
            1.0,
            1.0,
            1.0,
            1.0,
            1.0,
            1.0,
            1.0,
            1.0,
            1.0,
            1.0,
            1.0,
            1.0,
            1.0,
            1.0,
            1.0,
            1.0,
            1.0,
            1.0,
            1.0,
            1.0,
            1.0,
            1.0,
            1.0,
            1.0,
            1.0,
            1.0,
            1.0,
            1.0,
            1.0,
            1.0,
            1.0,
            1.0,
            1.0,
            1.0,
            1.0,
            1.0,
            1.0,
            1.0,
            1.0,
            1.0,
            1.0,
            1.0,
            1.0,
            1.0,
            1.0,
            0.46766827943298395,
            0.09116373822256177,
            0.061386979034037885,
            0.05627705627705628,
            0.05194805194805195,
            0.047619047619047616,
            0.046125116713352135,
            0.04339190221543153,
            0.047619047619047616,
            0.047619047619047616,
            0.04385026737967913,
            0.04329004329004329,
            0.042712842712842744,
            0.03896103896103896,
            0.03896103896103896,
            0.03896103896103896,
            0.03896103896103896,
            0.03588829471182421,
            0.03862150920974457,
            0.03463203463203463,
            0.03383413971649264,
            0.03383413971649264,
            0.03463203463203463,
            0.03463203463203463,
            0.030303030303030304,
            0.03463203463203463,
            0.03463203463203463,
            0.03201765554706723,
            0.03666921313980149,
            0.08484848484848495,
            0.1038961038961039,
            0.08489941431117906,
            0.06493506493506493,
            0.06060606060606061,
            0.05627705627705628,
            0.06209999151175633,
            0.07050335285629389,
            0.09019607843137221,
            0.13071895424836524,
            0.25846702317290227,
            0.7679653679653555,
            1.0,
            1.0,
            1.0,
            1.0,
            1.0,
            1.0,
            1.0,
            1.0,
            1.0,
            1.0,
            1.0,
            1.0,
            1.0,
            1.0,
            1.0,
            1.0,
            1.0,
            1.0,
            1.0,
            1.0,
            1.0,
            1.0,
            1.0,
            1.0,
            1.0,
            1.0,
            1.0,
            1.0,
            1.0,
            1.0,
            1.0,
            1.0,
            1.0,
            1.0,
            1.0,
            1.0,
            1.0,
            1.0,
            1.0,
            0.2562770562770634,
            0.06754944402003184,
            0.05194805194805195,
            0.05194805194805195,
            0.047619047619047616,
            0.05627705627705628,
            0.08099482217129292,
            0.07581699346405224,
            0.07894066717596135,
            0.07252355487649605,
            0.06493506493506493,
            0.06921313980137514,
            0.05473219590866643,
            0.06807571513453876,
            0.06060606060606061,
            0.06060606060606061,
            0.06420507596978202,
            0.047619047619047616,
            0.025974025974025976,
            0.025974025974025976,
            0.024649859943977812,
            0.03885918003565121,
            0.04347678465325507,
            0.04583651642475186,
            0.0625074272133098,
            0.14248366013072028,
            0.9103641456582661,
            1.0,
            1.0,
            1.0,
            1.0,
            1.0,
            1.0,
            1.0,
            1.0,
            1.0,
            1.0,
            1.0,
            1.0,
            1.0,
            1.0,
            1.0,
            1.0,
            1.0,
            1.0,
            1.0,
            1.0,
            1.0,
            1.0,
            1.0,
            1.0,
            1.0,
            1.0,
            1.0,
            1.0,
            1.0,
            1.0,
            1.0,
            1.0,
            1.0,
            1.0,
            1.0,
            1.0,
            1.0,
            1.0,
            1.0,
            1.0,
            1.0,
            1.0
          ],
          [
            0.03896103896103896,
            0.03463203463203463,
            0.030303030303030304,
            0.02643239113827349,
            0.025974025974025976,
            0.03395297512944572,
            0.026890756302521007,
            0.025974025974025976,
            0.026194720312367373,
            0.030303030303030304,
            0.030303030303030304,
            0.04281470163823105,
            0.05444359562006622,
            0.13976742212036342,
            0.25626007978949145,
            0.8670741023682196,
            1.0,
            1.0,
            1.0,
            1.0,
            1.0,
            1.0,
            1.0,
            1.0,
            1.0,
            1.0,
            1.0,
            1.0,
            1.0,
            1.0,
            1.0,
            1.0,
            1.0,
            1.0,
            1.0,
            1.0,
            1.0,
            1.0,
            1.0,
            1.0,
            1.0,
            1.0,
            1.0,
            1.0,
            1.0,
            1.0,
            1.0,
            1.0,
            1.0,
            1.0,
            1.0,
            1.0,
            1.0,
            1.0,
            1.0,
            1.0,
            1.0,
            1.0,
            1.0,
            1.0,
            1.0,
            1.0,
            1.0,
            1.0,
            1.0,
            0.7235379000084905,
            0.0922332569391397,
            0.04933367286308454,
            0.03924963924963923,
            0.03896103896103896,
            0.03463203463203463,
            0.03104999575587817,
            0.03463203463203463,
            0.03463203463203463,
            0.03463203463203463,
            0.03463203463203463,
            0.03896103896103896,
            0.03463203463203463,
            0.04003055767761651,
            0.03896103896103896,
            0.03896103896103896,
            0.04329004329004329,
            0.03896103896103896,
            0.04329004329004329,
            0.04329004329004329,
            0.04329004329004329,
            0.046328834564128625,
            0.047619047619047616,
            0.047619047619047616,
            0.047619047619047616,
            0.05194805194805195,
            0.05194805194805195,
            0.06097954333248442,
            0.1095492742551559,
            0.6841354723707732,
            1.0,
            1.0,
            1.0,
            1.0,
            1.0,
            1.0,
            1.0,
            1.0,
            1.0,
            1.0,
            1.0,
            1.0,
            1.0,
            1.0,
            1.0,
            1.0,
            1.0,
            1.0,
            1.0,
            1.0,
            1.0,
            1.0,
            1.0,
            1.0,
            1.0,
            1.0,
            1.0,
            1.0,
            1.0,
            1.0,
            1.0,
            1.0,
            1.0,
            1.0,
            1.0,
            1.0,
            1.0,
            1.0,
            0.6929462694168534,
            0.23089720736779426,
            0.16221033868092702,
            0.1500721500721499,
            0.09958407605466428,
            0.06926406926406926,
            0.06060606060606061,
            0.05627705627705628,
            0.05627705627705628,
            0.05627705627705628,
            0.06926406926406926,
            0.09055258467023156,
            0.14761055937526488,
            0.17351667939903104,
            0.1518207282913192,
            0.03704269586622505,
            0.030303030303030304,
            0.030303030303030304,
            0.030303030303030304,
            0.030303030303030304,
            0.032900432900433,
            0.03463203463203463,
            0.03463203463203463,
            0.03896103896103896,
            0.035175282234105765,
            0.03463203463203463,
            0.03896103896103896,
            0.03471691706985817,
            0.03896103896103896,
            0.0414056531703588,
            0.07321959086664954,
            0.042899584076055014,
            0.03896103896103896,
            0.03896103896103896,
            0.03896103896103896,
            0.039266615737204184,
            0.03896103896103896,
            0.044733044733044895,
            0.04746625923096525,
            0.05452847805788994,
            0.07753161870808965,
            0.3620575502928468,
            1.0,
            1.0,
            1.0,
            1.0,
            1.0,
            1.0,
            1.0,
            1.0,
            1.0,
            1.0,
            1.0,
            1.0,
            1.0,
            1.0,
            1.0,
            1.0,
            1.0,
            1.0,
            1.0,
            1.0,
            1.0,
            1.0,
            1.0,
            1.0,
            1.0,
            1.0,
            1.0,
            1.0,
            1.0,
            1.0,
            1.0,
            1.0,
            1.0,
            1.0,
            1.0,
            1.0,
            1.0,
            1.0,
            1.0,
            1.0,
            1.0,
            1.0,
            1.0,
            1.0,
            1.0,
            1.0,
            1.0,
            1.0,
            0.299668958492489,
            0.13178847296494622,
            0.038706391647568346,
            0.03164417282064367,
            0.030303030303030304,
            0.03442831678125814,
            0.025974025974025976,
            0.02936932348697041,
            0.025974025974025976,
            0.030303030303030304,
            0.030303030303030304,
            0.03463203463203463,
            0.030303030303030304,
            0.030303030303030304,
            0.030303030303030304,
            0.030303030303030304,
            0.030303030303030304,
            0.03896103896103896,
            0.04537815126050378,
            0.05627705627705628,
            0.05627705627705628,
            0.06517273576097084,
            0.09549274255156535,
            0.24059078176724516,
            1.0,
            1.0,
            1.0,
            1.0,
            1.0,
            1.0,
            1.0,
            1.0,
            0.5108225108225108
          ]
        ],
        "band_detector": {
          "band_rows": null,
          "bright_percentile": 99.5,
          "min_run_px": 25,
          "params": {
            "search_frac": [
              0.2,
              0.8
            ],
            "dark_percentile": 5.0,
            "bright_rel": 0.9,
            "strip_run_frac": 0.25,
            "row_join_gap": 3,
            "min_strip_h": 6,
            "max_strip_h": 110,
            "max_strip_gap": 160,
            "min_peak_frac": 0.02,
            "min_dynamic_range": 20.0,
            "median_blur": 3,
            "profile_length": 256,
            "lit_frac_level": 0.35,
            "max_lag": 8,
            "min_score": 0.45,
            "min_margin": 0.15,
            "use_swap_check": true,
            "block_level": 0.5,
            "close_px": 21,
            "edge_tol_px": 12
          }
        },
        "band_learned": "2026-07-19T16:18:21",
        "band_dwells": 2
      }
    }
  }
}